{
  "languageserver": {
    "ccls": {
      "command": "ccls",
      "filetypes": ["c", "cpp", "cuda", "objc", "objcpp"],
      "rootPatterns": ["compile_commands.json"],
      "initializationOptions": {
        "cache": {
          "directory": "/tmp/ccls_cache"
        },
        "client": {
          "snippetSupport": true
        }
      }
    }
  },
  "rust-analyzer.procMacro.enable": true,
  "rust-analyzer.cargo.loadOutDirsFromCheck": true,
  "rust-analyzer.inlayHints.refreshOnInsertMode": true,
  "rust-analyzer.updates.prompt": false,
  "rust-analyzer.updates.channel": "nightly",
  "rust-analyzer.diagnostics.enableExperimental": true

}
